<?xml version="1.0" encoding="UTF-8"?>
<trips>
    <trip who="hay-john-milton" role="secretary">
        <id>908</id>
        <role>secretary</role>
        <name>John Milton Hay</name>
        <start-date>1905-04-03</start-date>
        <end-date>1905-04-29</end-date>
        <country id="italy">Italy</country>
        <locale>Genoa,Nervi</locale>
        <remarks>Vacation trip for health reasons. Left U.S. March 17.</remarks>
        <created-by>wicentowskijc</created-by>
        <created-datetime>2010-02-27T14:35:48.889-04:00</created-datetime>
        <last-modified-by>wicentowskijc</last-modified-by>
        <last-modified-datetime>2010-02-27T14:35:48.889-04:00</last-modified-datetime>
    </trip>
    <trip who="hay-john-milton" role="secretary">
        <id>909</id>
        <role>secretary</role>
        <name>John Milton Hay</name>
        <start-date>1905-04-30</start-date>
        <end-date>1905-05-21</end-date>
        <country id="germany">Germany</country>
        <locale>Nauheim</locale>
        <remarks>Vacation trip for health reasons.</remarks>
        <created-by>wicentowskijc</created-by>
        <created-datetime>2010-02-27T14:35:48.889-04:00</created-datetime>
        <last-modified-by>wicentowskijc</last-modified-by>
        <last-modified-datetime>2010-02-27T14:35:48.889-04:00</last-modified-datetime>
    </trip>
    <trip who="hay-john-milton" role="secretary">
        <id>910</id>
        <role>secretary</role>
        <name>John Milton Hay</name>
        <start-date>1905-05-22</start-date>
        <end-date>1905-06-01</end-date>
        <country id="france">France</country>
        <locale>Paris</locale>
        <remarks>Vacation trip for health reasons.</remarks>
        <created-by>wicentowskijc</created-by>
        <created-datetime>2010-02-27T14:35:48.889-04:00</created-datetime>
        <last-modified-by>wicentowskijc</last-modified-by>
        <last-modified-datetime>2010-02-27T14:35:48.889-04:00</last-modified-datetime>
    </trip>
    <trip who="hay-john-milton" role="secretary">
        <id>911</id>
        <role>secretary</role>
        <name>John Milton Hay</name>
        <start-date>1905-06-02</start-date>
        <end-date>1905-06-07</end-date>
        <country id="united-kingdom">United Kingdom</country>
        <locale>London,Liverpool</locale>
        <remarks>Vacation trip for health reasons. Returned to U.S. June 15; died July 1.</remarks>
        <created-by>wicentowskijc</created-by>
        <created-datetime>2010-02-27T14:35:48.889-04:00</created-datetime>
        <last-modified-by>wicentowskijc</last-modified-by>
        <last-modified-datetime>2010-02-27T14:35:48.889-04:00</last-modified-datetime>
    </trip>
</trips>