<?xml version="1.0" encoding="UTF-8"?>
<trips>
    <trip who="roosevelt-theodore" role="president">
        <id>Travel-2655-president</id>
        <role>president</role>
        <name>Theodore Roosevelt</name>
        <start-date>1906-11-14</start-date>
        <end-date>1906-11-17</end-date>
        <country id="panama">Panama</country>
        <locale>Colon,Panama City</locale>
        <remarks>To inspect construction of Panama Canal. First visit abroad by any President or
            President-elect. Departed the U.S. November 9; returned to U.S. November 26.</remarks>
        <created-by>wicentowskijc</created-by>
        <created-datetime/>
        <last-modified-by>wicentowskijc</last-modified-by>
        <last-modified-datetime/>
    </trip>
</trips>